{
    "textures": {
		"0": "tardis:item/monster/dalek/brown/mid_bottom",
		"1": "tardis:item/disk/blacker_plastic",
		"2": "tardis:item/disk/silver_metal",
		"3": "tardis:item/monster/dalek/brass/bottom",
		"4": "tardis:item/food/jam",
		"5": "tardis:item/food/fish_finger",
		"particle": "tardis:item/disk/silver_metal"
	},
	"display": {
		"thirdperson_righthand": {
			"rotation": [75, 45, 0],
			"translation": [0, 2.5, 2],
			"scale": [0.375, 0.375, 0.375]
		},
		"thirdperson_lefthand": {
			"rotation": [75, 45, 0],
			"translation": [0, 2.5, 2],
			"scale": [0.375, 0.375, 0.375]
		},
		"firstperson_righthand": {
			"rotation": [0, 45, 0],
			"translation": [0, 4, 0],
			"scale": [0.4, 0.4, 0.4]
		},
		"firstperson_lefthand": {
			"rotation": [0, 225, 0],
			"translation": [0, 4, 0],
			"scale": [0.4, 0.4, 0.4]
		},
		"ground": {
			"scale": [0.25, 0.25, 0.25]
		},
		"gui": {
			"rotation": [30, 225, 0],
			"translation": [0, 0.5, 0],
			"scale": [0.625, 0.625, 0.625]
		},
		"head": {
			"scale": [0.75, 0.75, 0.75]
		},
		"fixed": {
			"rotation": [-180, -75, -90],
			"translation": [4, 0, -18.5],
			"scale": [2, 2, 2]
		}
	},
	"groups": [
		0,
		{
			"name": "buttons",
			"origin": [0, 0, 0],
			"color": 0,
			"children": [1, 2, 3, 4, 5, 6]
		},
		{
			"name": "surround",
			"origin": [12, 1.25, 4],
			"color": 0,
			"children": [7, 8, 9, 10, 11, 12, 13]
		},
		{
			"name": "copper_bottom",
			"origin": [12, 1.25, 4],
			"color": 0,
			"children": [14, 15, 16, 17, 18, 19, 20, 21, 22]
		},
		{
			"name": "copper_top",
			"origin": [12, 1.25, 4],
			"color": 0,
			"children": [23, 24, 25, 26, 27, 28, 29, 30, 31]
		},
		{
			"name": "lever",
			"origin": [12, 1.25, 4],
			"color": 0,
			"children": [32, 33, 34, 35, 36, 37, 38, 39, 40, 41, 42]
		},
		{
			"name": "settings",
			"origin": [0, 0, 0],
			"color": 0,
			"children": [43, 44, 45, 46, 47, 48, 49, 50]
		}
	]
}